action_trees/__init__.py
action_trees/action_item.py
action_trees/py.typed
action_trees/version.py
action_trees/examples/__init__.py
action_trees/examples/coffee_maker.py
action_trees-2.0.1.dist-info/LICENCE
action_trees-2.0.1.dist-info/METADATA
action_trees-2.0.1.dist-info/WHEEL
action_trees-2.0.1.dist-info/top_level.txt
action_trees-2.0.1.dist-info/RECORD
