Metadata-Version: 2.1
Name: action_trees
Version: 2.0.1
Summary: Action decomposition and execution framework
Author-email: Jev Kuznetsov <jev@roxautomation.com>
Classifier: Development Status :: 4 - Beta
Classifier: Intended Audience :: Developers
Classifier: Natural Language :: English
Classifier: Programming Language :: Python :: 3.11
Requires-Python: >=3.11
License-File: LICENCE
Provides-Extra: test
Requires-Dist: pytest>=3; extra == "test"
Requires-Dist: pytest-cov; extra == "test"
Requires-Dist: pytest-asyncio; extra == "test"
